hother/__init__.py
hother/cancelable/__init__.py
hother/cancelable/py.typed
hother/cancelable/types.py
hother/cancelable/core/__init__.py
hother/cancelable/core/cancelable.py
hother/cancelable/core/exceptions.py
hother/cancelable/core/models.py
hother/cancelable/core/registry.py
hother/cancelable/core/token.py
hother/cancelable/integrations/__init__.py
hother/cancelable/integrations/fastapi.py
hother/cancelable/sources/__init__.py
hother/cancelable/sources/base.py
hother/cancelable/sources/composite.py
hother/cancelable/sources/condition.py
hother/cancelable/sources/signal.py
hother/cancelable/sources/timeout.py
hother/cancelable/streaming/__init__.py
hother/cancelable/streaming/simulator/__init__.py
hother/cancelable/streaming/simulator/config.py
hother/cancelable/streaming/simulator/simulator.py
hother/cancelable/streaming/simulator/utils.py
hother/cancelable/utils/__init__.py
hother/cancelable/utils/anyio_bridge.py
hother/cancelable/utils/context_bridge.py
hother/cancelable/utils/decorators.py
hother/cancelable/utils/logging.py
hother/cancelable/utils/streams.py
hother/cancelable/utils/testing.py
hother/cancelable/utils/threading_bridge.py
hother_cancelable-0.11.2.dist-info/METADATA
hother_cancelable-0.11.2.dist-info/WHEEL
hother_cancelable-0.11.2.dist-info/licenses/LICENSE
hother_cancelable-0.11.2.dist-info/RECORD
