Metadata-Version: 2.4
Name: hother-cancelable
Version: 0.11.2
Summary: A comprehensive async cancellation system for Python streams
Project-URL: Homepage, https://github.com/hotherio/cancelable
Project-URL: Bug Tracker, https://github.com/hotherio/cancelable/issues
Project-URL: Source, https://github.com/hotherio/cancelable
Project-URL: Documentation, https://hotherio.github.io/cancelable/latest/
Author-email: Alexandre Quemy <alexandre@hother.io>
License-File: LICENSE
Classifier: Development Status :: 4 - Beta
Classifier: Framework :: AnyIO
Classifier: Framework :: AsyncIO
Classifier: Intended Audience :: Developers
Classifier: License :: OSI Approved :: MIT License
Classifier: Operating System :: OS Independent
Classifier: Programming Language :: Python :: 3
Classifier: Programming Language :: Python :: 3.13
Classifier: Programming Language :: Python :: 3.14
Classifier: Topic :: Software Development :: Libraries :: Python Modules
Classifier: Topic :: System :: Networking
Requires-Python: >=3.13
Requires-Dist: anyio>=4.9.0
Requires-Dist: psutil>=7.1.1
Requires-Dist: pydantic>=2.11.7
Provides-Extra: examples
Requires-Dist: google-genai>=1.43.0; extra == 'examples'
Requires-Dist: psutil; extra == 'examples'
Requires-Dist: pynput>=1.8.1; extra == 'examples'
Provides-Extra: fastapi
Requires-Dist: fastapi>=0.115.14; extra == 'fastapi'
